Workbook

Sheet spain_clean
A1: Number | B1: Name | C1: Position | D1: Date of Birth | E1: Age | F1: Nationality | G1: Birth Country | H1: Place of Birth | I1: Height | J1: Market Value | K1: Main Position | L1: Other Positions | M1: Nationality 1 | N1: Nationality 2 | O1: Nationality 3 | P1: Position 2 | Q1: Position 3 | R1: Region
A2: 1.0 | B2: Biel Ribas | C2: Goalkeeper | D2: Dec 2, 1985 | E2: 38 | F2: Spain | G2: Spain | H2: Palma de Mallorca | J2: 1.86 | M2: Spain | R2: =IFERROR(VLOOKUP(spain_clean[[#This Row],[Place of Birth]],region!A:B,2,FALSE),"") -> Comunidad Autónoma de las Islas Baleares
A3: 13.0 | B3: Roberto Santamaría | C3: Goalkeeper | D3: Feb 27, 1985 | E3: 39 | F3: Spain | G3: Spain | H3: Pamplona | J3: 1.83 | M3: Spain | R3: =IFERROR(VLOOKUP(spain_clean[[#This Row],[Place of Birth]],region!A:B,2,FALSE),"") -> Comunidad Foral de Navarra
B4: Miguel Ángel Ávila | C4: Goalkeeper | D4: Apr 18, 1985 | E4: 39 | F4: Spain | G4: Spain | H4: Torremolinos | J4: 1.82 | M4: Spain | R4: =IFERROR(VLOOKUP(spain_clean[[#This Row],[Place of Birth]],region!A:B,2,FALSE),"") -> Comunidad Autónoma de Andalucía
B5: Francisco Javier Rosales Simón | C5: Goalkeeper | D5: Dec 9, 1985 | E5: 38 | F5: Spain | G5: Spain | H5: La Linea de la Conceocion | J5: 1.8 | M5: Spain | R5: =IFERROR(VLOOKUP(spain_clean[[#This Row],[Place of Birth]],region!A:B,2,FALSE),"")
B6: Francisco Asta | C6: Goalkeeper | D6: Nov 4, 1985 | E6: 38 | F6: Spain | G6: Spain | H6: Almeria | J6: 1.83 | M6: Spain | R6: =IFERROR(VLOOKUP(spain_clean[[#This Row],[Place of Birth]],region!A:B,2,FALSE),"") -> Comunidad Autónoma de Andalucía
B7: Marcos Contreras | C7: Goalkeeper | D7: Aug 16, 1985 | E7: 38 | F7: Spain | G7: Spain | H7: Sevilla | J7: 1.83 | M7: Spain | R7: =IFERROR(VLOOKUP(spain_clean[[#This Row],[Place of Birth]],region!A:B,2,FALSE),"") -> Comunidad Autónoma de Andalucía
B8: Miguel Ángel Trenado | C8: Goalkeeper | D8: Jun 9, 1985 | E8: 39 | F8: Spain | G8: Spain | H8: Madrid | J8: 1.85 | M8: Spain | R8: =IFERROR(VLOOKUP(spain_clean[[#This Row],[Place of Birth]],region!A:B,2,FALSE),"") -> Comunidad de Madrid
B9: Guillermo Ubierna | C9: Goalkeeper | D9: Feb 27, 1985 | E9: 39 | F9: Spain | G9: Spain | H9: Alcobendas | J9: 1.9 | M9: Spain | R9: =IFERROR(VLOOKUP(spain_clean[[#This Row],[Place of Birth]],region!A:B,2,FALSE),"") -> Comunidad de Madrid
B10: Pablo Gómez | C10: Goalkeeper | D10: Sep 20, 1985 | E10: 38 | F10: Spain | G10: Spain | H10: Potes | J10: 1.83 | M10: Spain | R10: =IFERROR(VLOOKUP(spain_clean[[#This Row],[Place of Birth]],region!A:B,2,FALSE),"") -> Comunidad Autónoma de Cantabria
B11: Roberto Cirauqui | C11: Goalkeeper | D11: May 15, 1985 | E11: 39 | F11: Spain | G11: Spain | H11: Funes | J11: 1.86 | M11: Spain | R11: =IFERROR(VLOOKUP(spain_clean[[#This Row],[Place of Birth]],region!A:B,2,FALSE),"") -> Comunidad Foral de Navarra
B12: Dani Castro | C12: Goalkeeper | D12: Sep 24, 1985 | E12: 38 | F12: Spain | G12: Spain | H12: Gijon | J12: 1.88 | M12: Spain | R12: =IFERROR(VLOOKUP(spain_clean[[#This Row],[Place of Birth]],region!A:B,2,FALSE),"") -> Comunidad Autónoma del Principado de Asturias
B13: Raúl Sáez | C13: Goalkeeper | D13: Aug 20, 1985 | E13: 38 | F13: Spain | G13: Spain | H13: La Pobla de Mafumet | M13: Spain | R13: =IFERROR(VLOOKUP(spain_clean[[#This Row],[Place of Birth]],region!A:B,2,FALSE),"") -> Catalunya
B14: Jon Juanes | C14: Goalkeeper | D14: Jan 16, 1985 | E14: 39 | F14: Spain | G14: Spain | H14: Barakaldo | J14: 1.87 | M14: Spain | R14: =IFERROR(VLOOKUP(spain_clean[[#This Row],[Place of Birth]],region!A:B,2,FALSE),"") -> Euskal Autonomia Erkidegoa
A15: 13.0 | B15: Francisco Dorronsoro | C15: Goalkeeper | D15: May 22, 1985 | E15: 39 | F15: Spain | G15: Spain | H15: Torrelavega | J15: 1.8 | M15: Spain | R15: =IFERROR(VLOOKUP(spain_clean[[#This Row],[Place of Birth]],region!A:B,2,FALSE),"") -> Comunidad Autónoma de Cantabria
A16: 1.0 | B16: Jonay Quintana | C16: Goalkeeper | D16: Nov 27, 1985 | E16: 38 | F16: Spain | G16: Spain | H16: Las Palmas de Gran Canaria | M16: Spain | R16: =IFERROR(VLOOKUP(spain_clean[[#This Row],[Place of Birth]],region!A:B,2,FALSE),"") -> Comunidad Autónoma de Canarias
B17: David Larumbe | C17: Goalkeeper | D17: Jan 31, 1985 | E17: 39 | F17: Spain | G17: Spain | H17: Pamplona | M17: Spain | R17: =IFERROR(VLOOKUP(spain_clean[[#This Row],[Place of Birth]],region!A:B,2,FALSE),"") -> Comunidad Foral de Navarra
B18: Imanol Pérez | C18: Goalkeeper | D18: Jun 1, 1985 | E18: 39 | F18: Spain | G18: Spain | H18: Errenteria | J18: 1.85 | M18: Spain | R18: =IFERROR(VLOOKUP(spain_clean[[#This Row],[Place of Birth]],region!A:B,2,FALSE),"") -> Euskal Autonomia Erkidegoa
B19: Chato | C19: Goalkeeper | D19: Jan 4, 1985 | E19: 39 | F19: Spain | G19: Spain | H19: Tomelloso | M19: Spain | R19: =IFERROR(VLOOKUP(spain_clean[[#This Row],[Place of Birth]],region!A:B,2,FALSE),"") -> Comunidad Autónoma de Castilla-La Mancha
A20: 1.0 | B20: Manolo Delgado | C20: Goalkeeper | D20: May 21, 1985 | E20: 39 | F20: Spain | G20: Spain | H20: Manzanares | J20: 1.85 | M20: Spain | R20: =IFERROR(VLOOKUP(spain_clean[[#This Row],[Place of Birth]],region!A:B,2,FALSE),"") -> Comunidad Autónoma de Castilla-La Mancha
B21: Josué Castells | C21: Goalkeeper | D21: Jan 9, 1985 | E21: 39 | F21: Peru, Spain | G21: Spain | H21: Barcelona | M21: Peru | N21: Spain | R21: =IFERROR(VLOOKUP(spain_clean[[#This Row],[Place of Birth]],region!A:B,2,FALSE),"") -> Catalunya
B22: Chele | C22: Goalkeeper | D22: Mar 26, 1985 | E22: 39 | F22: Spain | G22: Spain | H22: Madrid | J22: 1.8 | M22: Spain | R22: =IFERROR(VLOOKUP(spain_clean[[#This Row],[Place of Birth]],region!A:B,2,FALSE),"") -> Comunidad de Madrid
B23: Roberto Román | C23: Goalkeeper | D23: Jul 4, 1985 | E23: 39 | F23: Spain | G23: Spain | H23: Caceres | J23: 1.89 | M23: Spain | R23: =IFERROR(VLOOKUP(spain_clean[[#This Row],[Place of Birth]],region!A:B,2,FALSE),"") -> Comunidad Autónoma de Extremadura
B24: Carlos Saavedra | C24: Goalkeeper | D24: May 3, 1985 | E24: 39 | F24: Spain | G24: Spain | H24: Madrid | J24: 1.87 | M24: Spain | R24: =IFERROR(VLOOKUP(spain_clean[[#This Row],[Place of Birth]],region!A:B,2,FALSE),"") -> Comunidad de Madrid
B25: Oier San Miguel | C25: Goalkeeper | D25: Jan 20, 1985 | E25: 39 | F25: Spain | G25: Spain | H25: Ondarroa | J25: 1.87 | M25: Spain | R25: =IFERROR(VLOOKUP(spain_clean[[#This Row],[Place of Birth]],region!A:B,2,FALSE),"") -> Euskal Autonomia Erkidegoa
B26: David Alemán | C26: Goalkeeper | D26: Feb 7, 1985 | E26: 39 | F26: Spain | G26: Spain | H26: Pajara | J26: 1.74 | M26: Spain | R26: =IFERROR(VLOOKUP(spain_clean[[#This Row],[Place of Birth]],region!A:B,2,FALSE),"") -> Comunidad Autónoma de Canarias
A27: 13.0 | B27: Nauzet Pérez | C27: Goalkeeper | D27: Mar 1, 1985 | E27: 39 | F27: Spain | G27: Portugal | H27: Las Palmas de Gran Canaria | J27: 1.9 | M27: Spain | R27: =IFERROR(VLOOKUP(spain_clean[[#This Row],[Place of Birth]],region!A:B,2,FALSE),"") -> Comunidad Autónoma de Canarias
B28: José Manuel Camacho | C28: Goalkeeper | D28: Jul 9, 1985 | E28: 39 | F28: Spain | G28: Portugal | H28: Jerez de la Frontera | J28: 1.82 | M28: Spain | R28: =IFERROR(VLOOKUP(spain_clean[[#This Row],[Place of Birth]],region!A:B,2,FALSE),"") -> Comunidad Autónoma de Andalucía
B29: Ariza | C29: Goalkeeper | D29: Apr 1, 1985 | E29: 39 | F29: Spain | G29: Portugal | H29: Malaga | J29: 1.82 | M29: Spain | R29: =IFERROR(VLOOKUP(spain_clean[[#This Row],[Place of Birth]],region!A:B,2,FALSE),"") -> Comunidad Autónoma de Andalucía
B30: Juan Manuel Torrente | C30: Goalkeeper | D30: Jun 1, 1985 | E30: 39 | F30: Spain | G30: Portugal | H30: Puerto Lumbreras | J30: 1.85 | M30: Spain | R30: =IFERROR(VLOOKUP(spain_clean[[#This Row],[Place of Birth]],region!A:B,2,FALSE),"") -> Comunidad Autónoma de la Región de Murcia
B31: Alberto García | C31: Goalkeeper | D31: Feb 9, 1985 | E31: 39 | F31: Spain | G31: Portugal | H31: Barcelona | J31: 1.82 | M31: Spain | R31: =IFERROR(VLOOKUP(spain_clean[[#This Row],[Place of Birth]],region!A:B,2,FALSE),"") -> Catalunya
B32: David Montero | C32: Goalkeeper | D32: Mar 12, 1985 | E32: 39 | F32: Spain | G32: Portugal | H32: Salamanca | J32: 1.81 | M32: Spain | R32: =IFERROR(VLOOKUP(spain_clean[[#This Row],[Place of Birth]],region!A:B,2,FALSE),"") -> Comunidad Autónoma de Castilla y León
B33: Aitor Alcalde | C33: Goalkeeper | D33: May 22, 1985 | E33: 39 | F33: Spain | G33: Portugal | H33: Erandio | J33: 1.86 | M33: Spain | R33: =IFERROR(VLOOKUP(spain_clean[[#This Row],[Place of Birth]],region!A:B,2,FALSE),"") -> Euskal Autonomia Erkidegoa
B34: Alberto Montero | C34: Goalkeeper | D34: Mar 28, 1985 | E34: 39 | F34: Spain | G34: Portugal | H34: Barcelona | J34: 1.86 | M34: Spain | R34: =IFERROR(VLOOKUP(spain_clean[[#This Row],[Place of Birth]],region!A:B,2,FALSE),"") -> Catalunya
B35: Sergio López | C35: Goalkeeper | D35: Oct 29, 1985 | E35: 38 | F35: Spain | G35: Portugal | H35: Santander | J35: 1.85 | M35: Spain | R35: =IFERROR(VLOOKUP(spain_clean[[#This Row],[Place of Birth]],region!A:B,2,FALSE),"") -> Comunidad Autónoma de Cantabria
B36: Manel Arroyo | C36: Goalkeeper | D36: Feb 21, 1985 | E36: 39 | F36: Spain | G36: Portugal | H36: Madrid | J36: 1.86 | M36: Spain | R36: =IFERROR(VLOOKUP(spain_clean[[#This Row],[Place of Birth]],region!A:B,2,FALSE),"") -> Comunidad de Madrid
B37: Jorge Larrosa | C37: Goalkeeper | D37: Dec 16, 1985 | E37: 38 | F37: Spain | G37: Portugal | H37: Huesca | J37: 1.81 | M37: Spain | R37: =IFERROR(VLOOKUP(spain_clean[[#This Row],[Place of Birth]],region!A:B,2,FALSE),"") -> Comunidad Autónoma de Aragón
B38: Darío Fernández | C38: Goalkeeper | D38: Jun 16, 1985 | E38: 39 | F38: Spain | G38: Portugal | H38: Granada | J38: 1.82 | M38: Spain | R38: =IFERROR(VLOOKUP(spain_clean[[#This Row],[Place of Birth]],region!A:B,2,FALSE),"") -> Comunidad Autónoma de Andalucía
B39: Dani | C39: Goalkeeper | D39: Apr 23, 1985 | E39: 39 | F39: Spain | G39: Portugal | H39: Cadiz | J39: 1.8 | M39: Spain | R39: =IFERROR(VLOOKUP(spain_clean[[#This Row],[Place of Birth]],region!A:B,2,FALSE),"") -> Comunidad Autónoma de Andalucía
... B41: Manolo Reina | C41: Goalkeeper | D41: Apr 1, 1985 | E41: 39 | F41: Spain | G41: Portugal | H41: Villanueva del Trabuco | J41: 1.86 | M41: Spain | R41: =IFERROR(VLOOKUP(spain_clean[[#This Row],[Place of Birth]],region!A:B,2,FALSE),"") -> Comunidad Autónoma de Andalucía
A42: 13.0 | B42: Andrés Fernández | C42: Goalkeeper | D42: Dec 16, 1986 | E42: 37 | F42: Spain | G42: Spain | H42: Alcantarilla | J42: 1.85 | M42: Spain | R42: =IFERROR(VLOOKUP(spain_clean[[#This Row],[Place of Birth]],region!A:B,2,FALSE),"") -> Comunidad Autónoma de la Región de Murcia
A43: 1.0 | B43: Jon Irazusta | C43: Goalkeeper | D43: Apr 30, 1986 | E43: 38 | F43: Spain | G43: Spain | H43: Usurbil | J43: 1.84 | M43: Spain | R43: =IFERROR(VLOOKUP(spain_clean[[#This Row],[Place of Birth]],region!A:B,2,FALSE),"") -> Euskal Autonomia Erkidegoa
B44: David Armengol | C44: Goalkeeper | D44: Jun 13, 1986 | E44: 38 | F44: Spain | G44: Spain | H44: Oviedo | J44: 1.82 | M44: Spain | R44: =IFERROR(VLOOKUP(spain_clean[[#This Row],[Place of Birth]],region!A:B,2,FALSE),"") -> Comunidad Autónoma del Principado de Asturias
A45: 1.0 | B45: David Cortegoso | C45: Goalkeeper | D45: Oct 9, 1986 | E45: 37 | F45: Spain | G45: Spain | H45: Redondela | M45: Spain | R45: =IFERROR(VLOOKUP(spain_clean[[#This Row],[Place of Birth]],region!A:B,2,FALSE),"") -> Comunidad Autónoma de Galicia
B46: Francisco Otero Martín | C46: Goalkeeper | D46: Nov 3, 1986 | E46: 37 | F46: Spain | G46: Spain | H46: Santa Cruz de Tenerife | M46: Spain | R46: =IFERROR(VLOOKUP(spain_clean[[#This Row],[Place of Birth]],region!A:B,2,FALSE),"") -> Comunidad Autónoma de Canarias
A47: 1.0 | B47: Francisco Fernández | C47: Goalkeeper | D47: Aug 28, 1986 | E47: 37 | F47: Spain | G47: Spain | H47: Tarifa | J47: 1.78 | M47: Spain | R47: =IFERROR(VLOOKUP(spain_clean[[#This Row],[Place of Birth]],region!A:B,2,FALSE),"") -> Comunidad Autónoma de Andalucía
B48: Ayoze Mentado | C48: Goalkeeper | D48: Mar 15, 1986 | E48: 38 | F48: Spain | G48: Spain | H48: Las Palmas de Gran Canaria | M48: Spain | R48: =IFERROR(VLOOKUP(spain_clean[[#This Row],[Place of Birth]],region!A:B,2,FALSE),"") -> Comunidad Autónoma de Canarias
B49: Nico Monclova | C49: Goalkeeper | D49: Aug 4, 1986 | E49: 37 | F49: Spain | G49: Spain | H49: Lora del Rio | M49: Spain | R49: =IFERROR(VLOOKUP(spain_clean[[#This Row],[Place of Birth]],region!A:B,2,FALSE),"") -> Comunidad Autónoma de Andalucía
B50: Javi Ríos | C50: Goalkeeper | D50: Apr 19, 1986 | E50: 38 | F50: Spain | G50: Spain | H50: Logrono | J50: 1.82 | M50: Spain | R50: =IFERROR(VLOOKUP(spain_clean[[#This Row],[Place of Birth]],region!A:B,2,FALSE),"") -> Comunidad Autónoma de La Rioja
B51: Fran Martínez | C51: Goalkeeper | D51: Mar 26, 1986 | E51: 38 | F51: Spain | G51: Spain | H51: Yecla | M51: Spain | R51: =IFERROR(VLOOKUP(spain_clean[[#This Row],[Place of Birth]],region!A:B,2,FALSE),"") -> Comunidad Autónoma de la Región de Murcia
B52: Toni Texeira | C52: Goalkeeper | D52: Jul 27, 1986 | E52: 37 | F52: Spain | G52: Spain | H52: Barcelona | J52: 1.76 | M52: Spain | R52: =IFERROR(VLOOKUP(spain_clean[[#This Row],[Place of Birth]],region!A:B,2,FALSE),"") -> Catalunya
B53: Li | C53: Goalkeeper | D53: Nov 11, 1986 | E53: 37 | F53: Spain | G53: Spain | H53: Las Palmas de Gran Canaria | J53: 1.83 | M53: Spain | R53: =IFERROR(VLOOKUP(spain_clean[[#This Row],[Place of Birth]],region!A:B,2,FALSE),"") -> Comunidad Autónoma de Canarias
B54: José Miguel Márquez | C54: Goalkeeper | D54: May 19, 1986 | E54: 38 | F54: Spain | G54: Spain | H54: Tocina | J54: 1.88 | M54: Spain | R54: =IFERROR(VLOOKUP(spain_clean[[#This Row],[Place of Birth]],region!A:B,2,FALSE),"") -> Comunidad Autónoma de Andalucía
B55: Kiko Casilla | C55: Goalkeeper | D55: Oct 2, 1986 | E55: 37 | F55: Spain | G55: Spain | H55: Alcover | J55: 1.91 | M55: Spain | R55: =IFERROR(VLOOKUP(spain_clean[[#This Row],[Place of Birth]],region!A:B,2,FALSE),"") -> Catalunya
A56: 13.0 | B56: Ian Mackay | C56: Goalkeeper | D56: Jul 14, 1986 | E56: 37 | F56: Spain, Scotland | G56: Spain | H56: A Coruna | J56: 1.81 | M56: Spain | N56: Scotland | R56: =IFERROR(VLOOKUP(spain_clean[[#This Row],[Place of Birth]],region!A:B,2,FALSE),"") -> Comunidad Autónoma de Galicia
A57: 13.0 | B57: Toño | C57: Goalkeeper | D57: Nov 23, 1986 | E57: 37 | F57: Spain | G57: Spain | H57: Logrono | J57: 1.91 | M57: Spain | R57: =IFERROR(VLOOKUP(spain_clean[[#This Row],[Place of Birth]],region!A:B,2,FALSE),"") -> Comunidad Autónoma de La Rioja
B58: Chuchi | C58: Goalkeeper | D58: Oct 4, 1986 | E58: 37 | F58: Spain | G58: Spain | H58: Murcia | J58: 1.87 | M58: Spain | R58: =IFERROR(VLOOKUP(spain_clean[[#This Row],[Place of Birth]],region!A:B,2,FALSE),"") -> Comunidad Autónoma de la Región de Murcia
B59: Víctor | C59: Goalkeeper | D59: May 10, 1986 | E59: 38 | F59: Spain | G59: Spain | H59: Santander | J59: 1.83 | M59: Spain | R59: =IFERROR(VLOOKUP(spain_clean[[#This Row],[Place of Birth]],region!A:B,2,FALSE),"") -> Comunidad Autónoma de Cantabria
B60: Álex Hernández | C60: Goalkeeper | D60: Jun 4, 1986 | E60: 38 | F60: Spain | G60: Spain | H60: Valladolid | J60: 1.88 | M60: Spain | R60: =IFERROR(VLOOKUP(spain_clean[[#This Row],[Place of Birth]],region!A:B,2,FALSE),"") -> Comunidad Autónoma de Castilla y León
B61: Iván Contreras | C61: Goalkeeper | D61: Aug 5, 1986 | E61: 37 | F61: Spain | G61: Spain | H61: Pamplona | M61: Spain | R61: =IFERROR(VLOOKUP(spain_clean[[#This Row],[Place of Birth]],region!A:B,2,FALSE),"") -> Comunidad Foral de Navarra
B62: Diego García | C62: Goalkeeper | D62: Mar 1, 1986 | E62: 38 | F62: Spain | G62: Spain | H62: Santander | J62: 1.83 | M62: Spain | R62: =IFERROR(VLOOKUP(spain_clean[[#This Row],[Place of Birth]],region!A:B,2,FALSE),"") -> Comunidad Autónoma de Cantabria
B63: Lolo Soler | C63: Goalkeeper | D63: Sep 17, 1986 | E63: 37 | F63: Spain | G63: Spain | H63: Torremolinos | J63: 1.88 | M63: Spain | R63: =IFERROR(VLOOKUP(spain_clean[[#This Row],[Place of Birth]],region!A:B,2,FALSE),"") -> Comunidad Autónoma de Andalucía
A64: 1.0 | B64: Fran Sánchez | C64: Goalkeeper | D64: May 20, 1986 | E64: 38 | F64: Spain | G64: Spain | H64: Utrera | J64: 1.81 | M64: Spain | R64: =IFERROR(VLOOKUP(spain_clean[[#This Row],[Place of Birth]],region!A:B,2,FALSE),"") -> Comunidad Autónoma de Andalucía
B65: Víctor Bocanegra | C65: Goalkeeper | D65: Jan 15, 1986 | E65: 38 | F65: Spain | G65: Spain | H65: Sevilla | J65: 1.83 | M65: Spain | R65: =IFERROR(VLOOKUP(spain_clean[[#This Row],[Place of Birth]],region!A:B,2,FALSE),"") -> Comunidad Autónoma de Andalucía
B66: Iker Arrillaga | C66: Goalkeeper | D66: Nov 2, 1986 | E66: 37 | F66: Spain | G66: Spain | H66: Elgoibar | J66: 1.82 | M66: Spain | R66: =IFERROR(VLOOKUP(spain_clean[[#This Row],[Place of Birth]],region!A:B,2,FALSE),"") -> Euskal Autonomia Erkidegoa
B67: Michi | C67: Goalkeeper | D67: Feb 27, 1986 | E67: 38 | F67: Spain | G67: Spain | H67: Coles | J67: 1.86 | M67: Spain | R67: =IFERROR(VLOOKUP(spain_clean[[#This Row],[Place of Birth]],region!A:B,2,FALSE),"") -> Comunidad Autónoma de Galicia
B68: Santi Hidalgo | C68: Goalkeeper | D68: Aug 17, 1986 | E68: 37 | F68: Spain | G68: Spain | H68: Las Palmas de Gran Canaria | J68: 1.79 | M68: Spain | R68: =IFERROR(VLOOKUP(spain_clean[[#This Row],[Place of Birth]],region!A:B,2,FALSE),"") -> Comunidad Autónoma de Canarias
B69: Manu Polo | C69: Goalkeeper | D69: Jan 31, 1986 | E69: 38 | F69: Spain | G69: Spain | H69: Madrid | J69: 1.85 | M69: Spain | R69: =IFERROR(VLOOKUP(spain_clean[[#This Row],[Place of Birth]],region!A:B,2,FALSE),"") -> Comunidad de Madrid
B70: Tudela | C70: Goalkeeper | D70: Aug 23, 1986 | E70: 37 | F70: Spain | G70: Spain | H70: Murcia | J70: 1.85 | M70: Spain | R70: =IFERROR(VLOOKUP(spain_clean[[#This Row],[Place of Birth]],region!A:B,2,FALSE),"") -> Comunidad Autónoma de la Región de Murcia
B71: Roberto Pérez | C71: Goalkeeper | D71: Mar 25, 1986 | E71: 38 | F71: Spain | G71: Spain | H71: El Berron | J71: 1.77 | M71: Spain | R71: =IFERROR(VLOOKUP(spain_clean[[#This Row],[Place of Birth]],region!A:B,2,FALSE),"")
B72: Xabi Irureta | C72: Goalkeeper | D72: Mar 21, 1986 | E72: 38 | F72: Spain | G72: Spain | H72: Berriatua | J72: 1.79 | M72: Spain | R72: =IFERROR(VLOOKUP(spain_clean[[#This Row],[Place of Birth]],region!A:B,2,FALSE),"") -> Euskal Autonomia Erkidegoa
B73: Damián Seijoso | C73: Goalkeeper | D73: Jan 15, 1986 | E73: 38 | F73: Spain | G73: Spain | H73: A Coruna | J73: 1.82 | M73: Spain | R73: =IFERROR(VLOOKUP(spain_clean[[#This Row],[Place of Birth]],region!A:B,2,FALSE),"") -> Comunidad Autónoma de Galicia
B74: Emilio José Hernández | C74: Goalkeeper | D74: Feb 14, 1986 | E74: 38 | F74: Spain | G74: Spain | H74: Madrid | J74: 1.75 | M74: Spain | R74: =IFERROR(VLOOKUP(spain_clean[[#This Row],[Place of Birth]],region!A:B,2,FALSE),"") -> Comunidad de Madrid
A75: 13.0 | B75: Nacho Gil | C75: Goalkeeper | D75: Nov 6, 1986 | E75: 37 | F75: Spain | G75: Spain | H75: Madrid | J75: 1.88 | M75: Spain | R75: =IFERROR(VLOOKUP(spain_clean[[#This Row],[Place of Birth]],region!A:B,2,FALSE),"") -> Comunidad de Madrid
B76: David Zamora | C76: Goalkeeper | D76: Mar 6, 1986 | E76: 38 | F76: Spain | G76: Spain | H76: Cadiz | J76: 1.9 | M76: Spain | R76: =IFERROR(VLOOKUP(spain_clean[[#This Row],[Place of Birth]],region!A:B,2,FALSE),"") -> Comunidad Autónoma de Andalucía
B77: Berto | C77: Goalkeeper | D77: Dec 26, 1986 | E77: 37 | F77: Spain | G77: Spain | H77: Ribadavia | J77: 1.73 | M77: Spain | R77: =IFERROR(VLOOKUP(spain_clean[[#This Row],[Place of Birth]],region!A:B,2,FALSE),"") -> Comunidad Autónoma de Galicia
B78: Javi López | C78: Goalkeeper | D78: Mar 4, 1986 | E78: 38 | F78: Spain | G78: Spain | H78: O Incio | J78: 1.81 | M78: Spain | R78: =IFERROR(VLOOKUP(spain_clean[[#This Row],[Place of Birth]],region!A:B,2,FALSE),"") -> Comunidad Autónoma de Galicia
B79: Gregorio | C79: Goalkeeper | D79: May 1, 1986 | E79: 38 | F79: Spain | G79: Spain | H79: Vilches | J79: 1.81 | M79: Spain | R79: =IFERROR(VLOOKUP(spain_clean[[#This Row],[Place of Birth]],region!A:B,2,FALSE),"") -> Comunidad Autónoma de Andalucía
B80: Xavi Ginard | C80: Goalkeeper | D80: Oct 11, 1986 | E80: 37 | F80: Spain | G80: Spain | H80: Arta | J80: 1.86 | M80: Spain | R80: =IFERROR(VLOOKUP(spain_clean[[#This Row],[Place of Birth]],region!A:B,2,FALSE),"") -> Comunidad Autónoma de las Islas Baleares
B81: Eladio Fernández | C81: Goalkeeper | D81: Apr 25, 1986 | E81: 38 | F81: Spain | G81: Spain | H81: Madrid | J81: 1.89 | M81: Spain | R81: =IFERROR(VLOOKUP(spain_clean[[#This Row],[Place of Birth]],region!A:B,2,FALSE),"") -> Comunidad de Madrid
B82: Diego López | C82: Goalkeeper | D82: Jun 15, 1986 | E82: 38 | F82: Spain | G82: Spain | H82: Cambre | J82: 1.78 | M82: Spain | R82: =IFERROR(VLOOKUP(spain_clean[[#This Row],[Place of Birth]],region!A:B,2,FALSE),"") -> Comunidad Autónoma de Galicia
B83: Gaizka Ruiz | C83: Goalkeeper | D83: Sep 24, 1986 | E83: 37 | F83: Spain | G83: Spain | H83: Vitoria | J83: 1.81 | M83: Spain | R83: =IFERROR(VLOOKUP(spain_clean[[#This Row],[Place of Birth]],region!A:B,2,FALSE),"")
B84: Escribano | C84: Goalkeeper | D84: Mar 26, 1986 | E84: 38 | F84: Spain | G84: Spain | H84: Madrid | J84: 1.88 | M84: Spain | R84: =IFERROR(VLOOKUP(spain_clean[[#This Row],[Place of Birth]],region!A:B,2,FALSE),"") -> Comunidad de Madrid
B85: Raúl Domínguez | C85: Goalkeeper | D85: Nov 1, 1986 | E85: 37 | F85: Spain | G85: Spain | H85: Saron | J85: 1.81 | M85: Spain | R85: =IFERROR(VLOOKUP(spain_clean[[#This Row],[Place of Birth]],region!A:B,2,FALSE),"")
B86: Arkaitz Crespo | C86: Goalkeeper | D86: Jan 20, 1986 | E86: 38 | F86: Spain | G86: Spain | H86: Bilbao | J86: 1.81 | M86: Spain | R86: =IFERROR(VLOOKUP(spain_clean[[#This Row],[Place of Birth]],region!A:B,2,FALSE),"") -> Euskal Autonomia Erkidegoa
B87: Rafa Martínez | C87: Goalkeeper | D87: Nov 11, 1986 | E87: 37 | F87: Spain | G87: Spain | H87: Ciudad Real | J87: 1.85 | M87: Spain | R87: =IFERROR(VLOOKUP(spain_clean[[#This Row],[Place of Birth]],region!A:B,2,FALSE),"") -> Comunidad Autónoma de Castilla-La Mancha
... B91: José Campaña | C91: Goalkeeper | D91: Aug 26, 1986 | E91: 37 | F91: Spain | G91: Spain | H91: Huetor Tajar | J91: 1.86 | M91: Spain | R91: =IFERROR(VLOOKUP(spain_clean[[#This Row],[Place of Birth]],region!A:B,2,FALSE),"")
A92: 13.0 | B92: Limones | C92: Goalkeeper | D92: Oct 17, 1986 | E92: 37 | F92: Spain | G92: Portugal | H92: Daimiel | J92: 1.92 | M92: Spain | R92: =IFERROR(VLOOKUP(spain_clean[[#This Row],[Place of Birth]],region!A:B,2,FALSE),"") -> Comunidad Autónoma de Castilla-La Mancha
B93: Lucas Sierra | C93: Goalkeeper | D93: Jun 19, 1986 | E93: 38 | F93: Spain | G93: Portugal | H93: Ourense | J93: 1.86 | M93: Spain | R93: =IFERROR(VLOOKUP(spain_clean[[#This Row],[Place of Birth]],region!A:B,2,FALSE),"") -> Comunidad Autónoma de Galicia
A94: 1.0 | B94: Miguel Ramos | C94: Goalkeeper | D94: Oct 5, 1986 | E94: 37 | F94: Spain | G94: Portugal | H94: Barcelona | J94: 1.82 | M94: Spain | R94: =IFERROR(VLOOKUP(spain_clean[[#This Row],[Place of Birth]],region!A:B,2,FALSE),"") -> Catalunya
B95: Roberto | C95: Goalkeeper | D95: Feb 10, 1986 | E95: 38 | F95: Spain | G95: Portugal | H95: Madrid | J95: 1.92 | M95: Spain | R95: =IFERROR(VLOOKUP(spain_clean[[#This Row],[Place of Birth]],region!A:B,2,FALSE),"") -> Comunidad de Madrid
B96: Sergio Sánchez | C96: Goalkeeper | D96: Sep 27, 1986 | E96: 37 | F96: Spain | G96: Portugal | H96: Madrid | J96: 1.81 | M96: Spain | R96: =IFERROR(VLOOKUP(spain_clean[[#This Row],[Place of Birth]],region!A:B,2,FALSE),"") -> Comunidad de Madrid
B97: Manu Fernández | C97: Goalkeeper | D97: May 9, 1986 | E97: 38 | F97: Spain | G97: Portugal | H97: Gijon | J97: 1.85 | M97: Spain | R97: =IFERROR(VLOOKUP(spain_clean[[#This Row],[Place of Birth]],region!A:B,2,FALSE),"") -> Comunidad Autónoma del Principado de Asturias
B98: Sergio Álvarez | C98: Goalkeeper | D98: Aug 3, 1986 | E98: 37 | F98: Spain | G98: Portugal | H98: Vilagarcia de Arousa | J98: 1.79 | M98: Spain | R98: =IFERROR(VLOOKUP(spain_clean[[#This Row],[Place of Birth]],region!A:B,2,FALSE),"") -> Comunidad Autónoma de Galicia
A99: 25.0 | B99: Vicente Guaita | C99: Goalkeeper | D99: Jan 10, 1987 | E99: 37 | F99: Spain | G99: Spain | H99: Torrent | J99: 1.9 | M99: Spain | R99: =IFERROR(VLOOKUP(spain_clean[[#This Row],[Place of Birth]],region!A:B,2,FALSE),"") -> Comunidad Valenciana
B100: Antonio Adán | C100: Goalkeeper | D100: May 13, 1987 | E100: 37 | F100: Spain | G100: Spain | H100: Madrid | J100: 1.9 | M100: Spain | R100: =IFERROR(VLOOKUP(spain_clean[[#This Row],[Place of Birth]],region!A:B,2,FALSE),"") -> Comunidad de Madrid
A101: 12.0 | B101: Elías Hartard | C101: Goalkeeper | D101: May 18, 1987 | E101: 37 | F101: Chile, Spain | G101: Spain | H101: Madrid | J101: 1.85 | M101: Chile | N101: Spain | R101: =IFERROR(VLOOKUP(spain_clean[[#This Row],[Place of Birth]],region!A:B,2,FALSE),"") -> Comunidad de Madrid
A102: 1.0 | B102: Alberto Benito | C102: Goalkeeper | D102: Apr 21, 1987 | E102: 37 | F102: Spain | G102: Spain | H102: L'Entregu | J102: 1.9 | M102: Spain | R102: =IFERROR(VLOOKUP(spain_clean[[#This Row],[Place of Birth]],region!A:B,2,FALSE),"")
A103: 31.0 | B103: Vicente Mansanet | C103: Goalkeeper | D103: Aug 19, 1987 | E103: 36 | F103: Spain | G103: Spain | H103: Simat de la Valldigna | J103: 1.96 | M103: Spain | R103: =IFERROR(VLOOKUP(spain_clean[[#This Row],[Place of Birth]],region!A:B,2,FALSE),"") -> Comunidad Valenciana
B104: Robi | C104: Goalkeeper | D104: Aug 18, 1987 | E104: 36 | F104: Spain | G104: Spain | M104: Spain | R104: =IFERROR(VLOOKUP(spain_clean[[#This Row],[Place of Birth]],region!A:B,2,FALSE),"")
...

Sheet region
A1: asciiname | B1: region
A2: Kingdom of Spain
A3: Andalusia | B3: Comunidad Autónoma de Andalucía
A4: Catalunya | B4: Catalunya
A5: Comunidad de Madrid | B5: Comunidad de Madrid
A6: Provincia de Madrid | B6: Comunidad de Madrid
A7: Provincia de Barcelona | B7: Catalunya
A8: Comunitat Valenciana | B8: Comunidad Valenciana
A9: Madrid | B9: Comunidad de Madrid
A10: Madrid | B10: Comunidad de Madrid
A11: Galicia | B11: Comunidad Autónoma de Galicia
A12: Provincia de Valencia | B12: Comunidad Valenciana
A13: Castilla y Leon | B13: Comunidad Autónoma de Castilla y León
A14: Euskal Autonomia Erkidegoa | B14: Euskal Autonomia Erkidegoa
... A16322: Claramunt | B16322: Catalunya

Sheet TCD
A1: Nationality 2 | B1: (Plusieurs éléments)
A3: Étiquettes de lignes | B3: Nombre de Name
A4: Albania | B4: 1
A5: Algeria | B5: 2
A6: Andorra | B6: 6
A7: Angola | B7: 1
A8: Argentina | B8: 13
A9: Armenia | B9: 1
A10: Australia | B10: 2
A11: Azerbaijan | B11: 1
A12: Belarus | B12: 1
A13: Belgium | B13: 4
A14: Bolivia | B14: 5
A15: Bosnia-Herzegovina | B15: 1
... A86: Total général | B86: 813
