Workbook

Sheet france_clean
A1: Number | B1: Name | C1: Position | D1: Date of Birth | E1: Age | F1: Nationality | G1: Birth Country | H1: Place of Birth | I1: Height | J1: Market Value | K1: Other Positions | L1: Nationality 1 | M1: Nationality 2 | N1: Position 2 | O1: Position 3 | P1: Region | Q1: Département | R1: Continent
A2: 16 | B2: Jean-Louis Leca | C2: Goalkeeper | D2: Sep 21, 1985 | E2: 38 | F2: France | G2: France | H2: Bastia | I2: 1.8 | J2: €200k | L2: France | P2: Corse | Q2: Haute-Corse | R2: =IFERROR(VLOOKUP(france_clean[[#This Row],[Nationality 1]],continent!A:B,2,FALSE),"") -> France
B3: Mathieu Suffissais | C3: Goalkeeper | D3: May 30, 1985 | E3: 38 | F3: France | G3: France | H3: Laval | I3: 1.83 | J3: - | L3: France | P3: Pays de la Loire | Q3: Mayenne | R3: =IFERROR(VLOOKUP(france_clean[[#This Row],[Nationality 1]],continent!A:B,2,FALSE),"") -> France
B4: Gérald Delaporte | C4: Goalkeeper | D4: Dec 18, 1985 | E4: 38 | F4: France | G4: France | J4: - | L4: France | R4: =IFERROR(VLOOKUP(france_clean[[#This Row],[Nationality 1]],continent!A:B,2,FALSE),"") -> France
B5: Thomas Fedrigo | C5: Goalkeeper | D5: May 10, 1985 | E5: 38 | F5: France, Italy | G5: France | H5: Paray-le-Monial | I5: 1.8 | J5: - | L5: France | M5: Italy | P5: Bourgogne-Franche-Comté | Q5: Saône-et-Loire | R5: =IFERROR(VLOOKUP(france_clean[[#This Row],[Nationality 1]],continent!A:B,2,FALSE),"") -> France
B6: Florian Piolot | C6: Goalkeeper | D6: Dec 24, 1985 | E6: 38 | F6: France | G6: France | H6: Pabu | I6: 1.86 | J6: - | L6: France | P6: Bretagne | Q6: Côtes-d'Armor | R6: =IFERROR(VLOOKUP(france_clean[[#This Row],[Nationality 1]],continent!A:B,2,FALSE),"") -> France
B7: Sébastien Callamand | C7: Goalkeeper | D7: Jun 26, 1985 | E7: 38 | F7: France | G7: France | H7: Oyonnax | I7: 1.86 | J7: - | L7: France | P7: Auvergne-Rhône-Alpes | Q7: Ain | R7: =IFERROR(VLOOKUP(france_clean[[#This Row],[Nationality 1]],continent!A:B,2,FALSE),"") -> France
B8: Foued Baba Alla | C8: Goalkeeper | D8: Sep 23, 1985 | E8: 38 | F8: Morocco, France | G8: France | H8: Graulhet | J8: - | L8: Morocco | M8: France | P8: Occitanie | Q8: Tarn | R8: =IFERROR(VLOOKUP(france_clean[[#This Row],[Nationality 1]],continent!A:B,2,FALSE),"") -> Africa
B9: Hadama Bathily | C9: Goalkeeper | D9: Jun 18, 1985 | E9: 38 | F9: France, Mali | G9: France | H9: Rouen | I9: 1.85 | J9: - | L9: France | M9: Mali | P9: Normandie | Q9: Seine-Maritime | R9: =IFERROR(VLOOKUP(france_clean[[#This Row],[Nationality 1]],continent!A:B,2,FALSE),"") -> France
B10: Florian Aït Ali | C10: Goalkeeper | D10: Jan 4, 1985 | E10: 39 | F10: France | G10: France | H10: Toulouse | I10: 1.76 | J10: - | L10: France | P10: Occitanie | Q10: Haute-Garonne | R10: =IFERROR(VLOOKUP(france_clean[[#This Row],[Nationality 1]],continent!A:B,2,FALSE),"") -> France
B11: Thomas Aupic | C11: Goalkeeper | D11: Feb 24, 1985 | E11: 39 | F11: France | G11: France | H11: Dijon | I11: 1.77 | J11: - | L11: France | P11: Bourgogne-Franche-Comté | Q11: Côte-d'Or | R11: =IFERROR(VLOOKUP(france_clean[[#This Row],[Nationality 1]],continent!A:B,2,FALSE),"") -> France
B12: Arnaud Ribeiro | C12: Goalkeeper | D12: Jun 6, 1985 | E12: 38 | F12: France | G12: France | H12: Lagny-sur-Marne | I12: 1.86 | J12: - | L12: France | P12: Île-de-France | Q12: Seine-et-Marne | R12: =IFERROR(VLOOKUP(france_clean[[#This Row],[Nationality 1]],continent!A:B,2,FALSE),"") -> France
B13: Gregory Douard | C13: Goalkeeper | D13: Aug 1, 1985 | E13: 38 | F13: France | G13: France | H13: Chateaubriant | I13: 1.8 | J13: - | L13: France | R13: =IFERROR(VLOOKUP(france_clean[[#This Row],[Nationality 1]],continent!A:B,2,FALSE),"") -> France
B14: Christopher Pilar | C14: Goalkeeper | D14: Mar 29, 1985 | E14: 38 | F14: Portugal, France | G14: France | H14: Dijon | I14: 1.85 | J14: - | L14: Portugal | M14: France | P14: Bourgogne-Franche-Comté | Q14: Côte-d'Or | R14: =IFERROR(VLOOKUP(france_clean[[#This Row],[Nationality 1]],continent!A:B,2,FALSE),"") -> Europe
B15: Sébastien Jaffré | C15: Goalkeeper | D15: Jan 26, 1985 | E15: 39 | F15: France | G15: France | H15: Morlaix | J15: - | L15: France | P15: Bretagne | Q15: Finistère | R15: =IFERROR(VLOOKUP(france_clean[[#This Row],[Nationality 1]],continent!A:B,2,FALSE),"") -> France
B16: Arnaud Maillot | C16: Goalkeeper | D16: Mar 12, 1985 | E16: 38 | F16: France | G16: France | H16: Besancon | I16: 1.78 | J16: - | L16: France | P16: Bourgogne-Franche-Comté | Q16: Doubs | R16: =IFERROR(VLOOKUP(france_clean[[#This Row],[Nationality 1]],continent!A:B,2,FALSE),"") -> France
B17: Benjamin Rytlewski | C17: Goalkeeper | D17: Dec 26, 1985 | E17: 38 | F17: France, Poland | G17: France | H17: Bethune | I17: 1.86 | J17: - | L17: France | M17: Poland | P17: Hauts-de-France | Q17: Pas-de-Calais | R17: =IFERROR(VLOOKUP(france_clean[[#This Row],[Nationality 1]],continent!A:B,2,FALSE),"") -> France
A18: 30 | B18: Stéphane Schneider | C18: Goalkeeper | D18: Jan 3, 1985 | E18: 39 | F18: France | G18: France | H18: Strasbourg | I18: 1.87 | J18: - | L18: France | P18: Grand Est | Q18: Bas-Rhin | R18: =IFERROR(VLOOKUP(france_clean[[#This Row],[Nationality 1]],continent!A:B,2,FALSE),"") -> France
B19: Guillaume Garnier | C19: Goalkeeper | D19: Jul 5, 1985 | E19: 38 | F19: France | G19: France | H19: Mantes-la-Jolie | J19: - | L19: France | P19: Île-de-France | Q19: Yvelines | R19: =IFERROR(VLOOKUP(france_clean[[#This Row],[Nationality 1]],continent!A:B,2,FALSE),"") -> France
B20: Nicolas D'Alessio | C20: Goalkeeper | D20: Dec 24, 1985 | E20: 38 | F20: France | G20: France | I20: 1.84 | J20: - | L20: France | R20: =IFERROR(VLOOKUP(france_clean[[#This Row],[Nationality 1]],continent!A:B,2,FALSE),"") -> France
B21: Lucas Rastello | C21: Goalkeeper | D21: Apr 21, 1985 | E21: 38 | F21: France | G21: France | H21: Marseille | I21: 1.79 | J21: - | L21: France | P21: Provence-Alpes-Côte d'Azur | Q21: Bouches-du-Rhône | R21: =IFERROR(VLOOKUP(france_clean[[#This Row],[Nationality 1]],continent!A:B,2,FALSE),"") -> France
B22: Cédric Si Mohammed | C22: Goalkeeper | D22: Jan 9, 1985 | E22: 39 | F22: Algeria, France | G22: France | H22: Roanne | I22: 1.83 | J22: - | L22: Algeria | M22: France | P22: Auvergne-Rhône-Alpes | Q22: Loire | R22: =IFERROR(VLOOKUP(france_clean[[#This Row],[Nationality 1]],continent!A:B,2,FALSE),"") -> Africa
B23: Clément Maury | C23: Goalkeeper | D23: Nov 20, 1985 | E23: 38 | F23: France | G23: France | H23: Aurillac | I23: 1.82 | J23: - | L23: France | P23: Auvergne-Rhône-Alpes | Q23: Cantal | R23: =IFERROR(VLOOKUP(france_clean[[#This Row],[Nationality 1]],continent!A:B,2,FALSE),"") -> France
B24: Yann Hubert | C24: Goalkeeper | D24: Jan 9, 1985 | E24: 39 | F24: France | G24: France | H24: Nimes | I24: 1.86 | J24: - | L24: France | P24: Occitanie | Q24: Gard | R24: =IFERROR(VLOOKUP(france_clean[[#This Row],[Nationality 1]],continent!A:B,2,FALSE),"") -> France
B25: Adrien Gato | C25: Goalkeeper | D25: Dec 16, 1985 | E25: 38 | F25: France | G25: France | H25: Neuilly-sur-Seine | I25: 1.74 | J25: - | L25: France | P25: Île-de-France | Q25: Hauts-de-Seine | R25: =IFERROR(VLOOKUP(france_clean[[#This Row],[Nationality 1]],continent!A:B,2,FALSE),"") -> France
B26: Gaëtan Deneuve | C26: Goalkeeper | D26: May 3, 1985 | E26: 38 | F26: France | G26: France | H26: Harfleur | I26: 1.83 | J26: - | L26: France | P26: Normandie | Q26: Seine-Maritime | R26: =IFERROR(VLOOKUP(france_clean[[#This Row],[Nationality 1]],continent!A:B,2,FALSE),"") -> France
B27: Mickael Castejon | C27: Goalkeeper | D27: Mar 21, 1985 | E27: 38 | F27: France, Spain | G27: France | H27: Libourne | I27: 1.81 | J27: - | L27: France | M27: Spain | P27: Nouvelle-Aquitaine | Q27: Gironde | R27: =IFERROR(VLOOKUP(france_clean[[#This Row],[Nationality 1]],continent!A:B,2,FALSE),"") -> France
B28: Fabien Farnolle | C28: Goalkeeper | D28: Feb 5, 1985 | E28: 39 | F28: Benin, France | G28: France | H28: Bordeaux | I28: 1.97 | J28: - | L28: Benin | M28: France | P28: Nouvelle-Aquitaine | Q28: Gironde | R28: =IFERROR(VLOOKUP(france_clean[[#This Row],[Nationality 1]],continent!A:B,2,FALSE),"") -> Africa
B29: Simon Pouplin | C29: Goalkeeper | D29: May 28, 1985 | E29: 38 | F29: France | G29: France | H29: Cholet | J29: - | L29: France | P29: Pays de la Loire | Q29: Maine-et-Loire | R29: =IFERROR(VLOOKUP(france_clean[[#This Row],[Nationality 1]],continent!A:B,2,FALSE),"") -> France
B30: Benoît Benvegnu | C30: Goalkeeper | D30: Jan 18, 1985 | E30: 39 | F30: France | G30: France | H30: Montauban | I30: 1.84 | J30: - | L30: France | P30: Occitanie | Q30: Tarn-et-Garonne | R30: =IFERROR(VLOOKUP(france_clean[[#This Row],[Nationality 1]],continent!A:B,2,FALSE),"") -> France
A31: 22 | B31: Alexandre Martinovic | C31: Goalkeeper | D31: May 31, 1985 | E31: 38 | F31: France, Montenegro | G31: France | H31: Montbeliard | I31: 1.93 | J31: - | L31: France | M31: Montenegro | P31: Bourgogne-Franche-Comté | Q31: Doubs | R31: =IFERROR(VLOOKUP(france_clean[[#This Row],[Nationality 1]],continent!A:B,2,FALSE),"") -> France
B32: Johan Lapeyre | C32: Goalkeeper | D32: Aug 3, 1985 | E32: 38 | F32: France | G32: France | H32: Le Plessis-Bouchard | I32: 1.78 | J32: - | L32: France | P32: Île-de-France | Q32: Val-d'Oise | R32: =IFERROR(VLOOKUP(france_clean[[#This Row],[Nationality 1]],continent!A:B,2,FALSE),"") -> France
B33: Nicolas Cousin | C33: Goalkeeper | D33: Jul 11, 1985 | E33: 38 | F33: France | G33: France | H33: Nemours | I33: 1.84 | J33: - | L33: France | P33: Île-de-France | Q33: Seine-et-Marne | R33: =IFERROR(VLOOKUP(france_clean[[#This Row],[Nationality 1]],continent!A:B,2,FALSE),"") -> France
B34: Alexis Thébaux | C34: Goalkeeper | D34: Mar 17, 1985 | E34: 38 | F34: France | G34: France | H34: Les Sables-d'Olonne | I34: 1.85 | J34: - | L34: France | P34: Pays de la Loire | Q34: Vendée | R34: =IFERROR(VLOOKUP(france_clean[[#This Row],[Nationality 1]],continent!A:B,2,FALSE),"") -> France
A35: 24 | B35: Yohann Lacroix | C35: Goalkeeper | D35: Feb 1, 1985 | E35: 39 | F35: France | G35: France | H35: Thonon-les-Bains | I35: 1.94 | J35: - | L35: France | P35: Auvergne-Rhône-Alpes | Q35: Haute-Savoie | R35: =IFERROR(VLOOKUP(france_clean[[#This Row],[Nationality 1]],continent!A:B,2,FALSE),"") -> France
B36: Wilfried Bulgare | C36: Goalkeeper | D36: Feb 26, 1985 | E36: 39 | F36: Martinique, France | G36: France | H36: Toulon | I36: 1.78 | J36: - | L36: Martinique | M36: France | P36: Provence-Alpes-Côte d'Azur | Q36: Var | R36: =IFERROR(VLOOKUP(france_clean[[#This Row],[Nationality 1]],continent!A:B,2,FALSE),"") -> North America
A37: 1 | B37: Hugo Lloris | C37: Goalkeeper | D37: Dec 26, 1986 | E37: 37 | F37: France | G37: France | H37: Nice | I37: 1.88 | J37: €1.50m | L37: France | P37: Provence-Alpes-Côte d'Azur | Q37: Alpes-Maritimes | R37: =IFERROR(VLOOKUP(france_clean[[#This Row],[Nationality 1]],continent!A:B,2,FALSE),"") -> France
A38: 23 | B38: Raïs M'Bolhi | C38: Goalkeeper | D38: Apr 25, 1986 | E38: 37 | F38: Algeria, France | G38: France | H38: Paris | I38: 1.9 | J38: €200k | L38: Algeria | M38: France | P38: Île-de-France | Q38: Paris | R38: =IFERROR(VLOOKUP(france_clean[[#This Row],[Nationality 1]],continent!A:B,2,FALSE),"") -> Africa
B39: Jérôme Mançon | C39: Goalkeeper | D39: Jan 10, 1986 | E39: 38 | F39: France | G39: France | H39: Marcq-en-Baroeul | I39: 1.77 | J39: - | L39: France | R39: =IFERROR(VLOOKUP(france_clean[[#This Row],[Nationality 1]],continent!A:B,2,FALSE),"") -> France
B40: Julien Fondraz | C40: Goalkeeper | D40: Jun 25, 1986 | E40: 37 | F40: France | G40: France | H40: Coutances | J40: - | L40: France | P40: Normandie | Q40: Manche | R40: =IFERROR(VLOOKUP(france_clean[[#This Row],[Nationality 1]],continent!A:B,2,FALSE),"") -> France
B41: Thomas Valverde | C41: Goalkeeper | D41: Aug 6, 1986 | E41: 37 | F41: France | G41: France | H41: Paris | I41: 1.8 | J41: - | L41: France | P41: Île-de-France | Q41: Paris | R41: =IFERROR(VLOOKUP(france_clean[[#This Row],[Nationality 1]],continent!A:B,2,FALSE),"") -> France
B42: Ludovic Rose-Antoinette | C42: Goalkeeper | D42: Jun 24, 1986 | E42: 37 | F42: France, Martinique | G42: France | H42: Paris | I42: 1.84 | J42: - | L42: France | M42: Martinique | P42: Île-de-France | Q42: Paris | R42: =IFERROR(VLOOKUP(france_clean[[#This Row],[Nationality 1]],continent!A:B,2,FALSE),"") -> France
B43: Nicolas Zaccarelli | C43: Goalkeeper | D43: Oct 20, 1986 | E43: 37 | F43: France | G43: France | H43: Noisy-le-Grand | I43: 1.86 | J43: - | L43: France | P43: Île-de-France | Q43: Seine-Saint-Denis | R43: =IFERROR(VLOOKUP(france_clean[[#This Row],[Nationality 1]],continent!A:B,2,FALSE),"") -> France
B44: Jean-François Lecomte | C44: Goalkeeper | D44: Jul 23, 1986 | E44: 37 | F44: France | G44: France | H44: Hazebrouck | I44: 1.82 | J44: - | L44: France | P44: Hauts-de-France | Q44: Nord | R44: =IFERROR(VLOOKUP(france_clean[[#This Row],[Nationality 1]],continent!A:B,2,FALSE),"") -> France
B45: Nicolas Paul | C45: Goalkeeper | D45: Feb 3, 1986 | E45: 38 | F45: France, Réunion | G45: France | H45: Nantes | I45: 1.81 | J45: - | L45: France | M45: Réunion | P45: Pays de la Loire | Q45: Loire-Atlantique | R45: =IFERROR(VLOOKUP(france_clean[[#This Row],[Nationality 1]],continent!A:B,2,FALSE),"") -> France
B46: Fatih Öztürk | C46: Goalkeeper | D46: Dec 22, 1986 | E46: 37 | F46: Türkiye | G46: France | H46: Phalsbourg | I46: 1.91 | J46: - | L46: Türkiye | P46: Grand Est | Q46: Moselle | R46: =IFERROR(VLOOKUP(france_clean[[#This Row],[Nationality 1]],continent!A:B,2,FALSE),"") -> Asia
B47: David | C47: Goalkeeper | D47: Aug 12, 1986 | E47: 37 | F47: Spain | G47: France | H47: Vaison la Romaine | I47: 1.75 | J47: - | L47: Spain | R47: =IFERROR(VLOOKUP(france_clean[[#This Row],[Nationality 1]],continent!A:B,2,FALSE),"") -> Europe
B48: Damien Vandionant | C48: Goalkeeper | D48: Feb 24, 1986 | E48: 38 | F48: France | G48: France | H48: Lens | I48: 1.89 | J48: - | L48: France | P48: Hauts-de-France | Q48: Pas-de-Calais | R48: =IFERROR(VLOOKUP(france_clean[[#This Row],[Nationality 1]],continent!A:B,2,FALSE),"") -> France
B49: Julien Robinet | C49: Goalkeeper | D49: Sep 12, 1986 | E49: 37 | F49: France | G49: France | H49: Saint-Raphael | I49: 1.84 | J49: - | L49: France | R49: =IFERROR(VLOOKUP(france_clean[[#This Row],[Nationality 1]],continent!A:B,2,FALSE),"") -> France
A50: 1 | B50: Régis Gurtner | C50: Goalkeeper | D50: Dec 8, 1986 | E50: 37 | F50: France | G50: France | H50: Saverne | I50: 1.82 | J50: €250k | L50: France | P50: Grand Est | Q50: Bas-Rhin | R50: =IFERROR(VLOOKUP(france_clean[[#This Row],[Nationality 1]],continent!A:B,2,FALSE),"") -> France
A51: 31 | B51: Quentin Westberg | C51: Goalkeeper | D51: Apr 25, 1986 | E51: 37 | F51: United States, France | G51: France | H51: Suresnes | I51: 1.83 | J51: €100k | L51: United States | M51: France | P51: Île-de-France | Q51: Hauts-de-Seine | R51: =IFERROR(VLOOKUP(france_clean[[#This Row],[Nationality 1]],continent!A:B,2,FALSE),"") -> North America
B52: Jeoffrey Dauphy | C52: Goalkeeper | D52: Jan 20, 1986 | E52: 38 | F52: France | G52: France | H52: Quessy | I52: 1.86 | J52: - | L52: France | P52: 0 | Q52: 0 | R52: =IFERROR(VLOOKUP(france_clean[[#This Row],[Nationality 1]],continent!A:B,2,FALSE),"") -> France
B53: Rémy Dhelemme | C53: Goalkeeper | D53: Jan 23, 1986 | E53: 38 | F53: France | G53: France | H53: Douai | J53: - | L53: France | P53: Hauts-de-France | Q53: Nord | R53: =IFERROR(VLOOKUP(france_clean[[#This Row],[Nationality 1]],continent!A:B,2,FALSE),"") -> France
B54: Hamady Niasse | C54: Goalkeeper | D54: Jul 3, 1986 | E54: 37 | F54: France, Senegal | G54: France | H54: Trappes | I54: 1.89 | J54: - | L54: France | M54: Senegal | P54: Île-de-France | Q54: Yvelines | R54: =IFERROR(VLOOKUP(france_clean[[#This Row],[Nationality 1]],continent!A:B,2,FALSE),"") -> France
B55: Geoffrey Saintot | C55: Goalkeeper | D55: Mar 28, 1986 | E55: 37 | F55: France | G55: France | H55: Avignon | I55: 1.91 | J55: - | L55: France | P55: Provence-Alpes-Côte d'Azur | Q55: Vaucluse | R55: =IFERROR(VLOOKUP(france_clean[[#This Row],[Nationality 1]],continent!A:B,2,FALSE),"") -> France
B56: Romain Crétin | C56: Goalkeeper | D56: Feb 20, 1986 | E56: 38 | F56: France | G56: France | H56: Gleize | I56: 1.84 | J56: - | L56: France | P56: Auvergne-Rhône-Alpes | Q56: Rhône | R56: =IFERROR(VLOOKUP(france_clean[[#This Row],[Nationality 1]],continent!A:B,2,FALSE),"") -> France
B57: Yannick Martin | C57: Goalkeeper | D57: Apr 27, 1986 | E57: 37 | F57: France | G57: France | H57: Bron | I57: 1.84 | J57: - | L57: France | P57: Auvergne-Rhône-Alpes | Q57: Rhône | R57: =IFERROR(VLOOKUP(france_clean[[#This Row],[Nationality 1]],continent!A:B,2,FALSE),"") -> France
B58: Armand Mendy | C58: Goalkeeper | D58: Dec 23, 1986 | E58: 37 | F58: France, Senegal | G58: France | H58: Le Havre | I58: 1.8 | J58: - | L58: France | M58: Senegal | P58: Normandie | Q58: Seine-Maritime | R58: =IFERROR(VLOOKUP(france_clean[[#This Row],[Nationality 1]],continent!A:B,2,FALSE),"") -> France
B59: Amaury Borel | C59: Goalkeeper | D59: Nov 8, 1986 | E59: 37 | F59: France | G59: France | H59: Cavaillon | I59: 1.87 | J59: - | L59: France | P59: Provence-Alpes-Côte d'Azur | Q59: Vaucluse | R59: =IFERROR(VLOOKUP(france_clean[[#This Row],[Nationality 1]],continent!A:B,2,FALSE),"") -> France
B60: Thomas Lacherez | C60: Goalkeeper | D60: Feb 8, 1986 | E60: 38 | F60: France | G60: France | H60: Cambrai | I60: 1.78 | J60: - | L60: France | P60: Hauts-de-France | Q60: Nord | R60: =IFERROR(VLOOKUP(france_clean[[#This Row],[Nationality 1]],continent!A:B,2,FALSE),"") -> France
B61: Florent Cabassud | C61: Goalkeeper | D61: Jul 9, 1986 | E61: 37 | F61: France | G61: France | H61: Orange | J61: - | L61: France | P61: Provence-Alpes-Côte d'Azur | Q61: Vaucluse | R61: =IFERROR(VLOOKUP(france_clean[[#This Row],[Nationality 1]],continent!A:B,2,FALSE),"") -> France
B62: Julien Vanni | C62: Goalkeeper | D62: May 28, 1986 | E62: 37 | F62: France | G62: France | H62: Manosque | I62: 1.83 | J62: - | L62: France | P62: Provence-Alpes-Côte d'Azur | Q62: Alpes-de-Haute-Provence | R62: =IFERROR(VLOOKUP(france_clean[[#This Row],[Nationality 1]],continent!A:B,2,FALSE),"") -> France
A63: 1 | B63: Yoann Djidonou | C63: Goalkeeper | D63: May 17, 1986 | E63: 37 | F63: Benin, France | G63: France | H63: Domont | J63: - | L63: Benin | M63: France | P63: Île-de-France | Q63: Val-d'Oise | R63: =IFERROR(VLOOKUP(france_clean[[#This Row],[Nationality 1]],continent!A:B,2,FALSE),"") -> Africa
B64: Mathieu Inthasane | C64: Goalkeeper | D64: Jun 8, 1986 | E64: 37 | F64: France, Laos | G64: France | H64: Tours | I64: 1.83 | J64: - | L64: France | M64: Laos | P64: Centre-Val de Loire | Q64: Indre-et-Loire | R64: =IFERROR(VLOOKUP(france_clean[[#This Row],[Nationality 1]],continent!A:B,2,FALSE),"") -> France
B65: Thomas Chatalen | C65: Goalkeeper | D65: Oct 31, 1986 | E65: 37 | F65: France | G65: France | H65: Rueil-Malmaison | I65: 1.76 | J65: - | L65: France | P65: Île-de-France | Q65: Hauts-de-Seine | R65: =IFERROR(VLOOKUP(france_clean[[#This Row],[Nationality 1]],continent!A:B,2,FALSE),"") -> France
B66: Jérémy Deichelbohrer | C66: Goalkeeper | D66: Apr 25, 1986 | E66: 37 | F66: France | G66: France | H66: Belfort | I66: 1.86 | J66: - | L66: France | P66: Bourgogne-Franche-Comté | Q66: Territoire de Belfort | R66: =IFERROR(VLOOKUP(france_clean[[#This Row],[Nationality 1]],continent!A:B,2,FALSE),"") -> France
B67: Stéphane Ruffier | C67: Goalkeeper | D67: Sep 27, 1986 | E67: 37 | F67: France | G67: France | H67: Bayonne | I67: 1.88 | J67: - | L67: France | P67: Nouvelle-Aquitaine | Q67: Pyrénées-Atlantiques | R67: =IFERROR(VLOOKUP(france_clean[[#This Row],[Nationality 1]],continent!A:B,2,FALSE),"") -> France
B68: Arnaud Brocard | C68: Goalkeeper | D68: Aug 19, 1986 | E68: 37 | F68: France | G68: France | H68: Dijon | I68: 1.85 | J68: - | L68: France | P68: Bourgogne-Franche-Comté | Q68: Côte-d'Or | R68: =IFERROR(VLOOKUP(france_clean[[#This Row],[Nationality 1]],continent!A:B,2,FALSE),"") -> France
B69: Benoît Tardieu | C69: Goalkeeper | D69: Jan 21, 1986 | E69: 38 | F69: Benin, France | G69: France | H69: Ussel | I69: 1.88 | J69: - | L69: Benin | M69: France | P69: Auvergne-Rhône-Alpes | Q69: Cantal | R69: =IFERROR(VLOOKUP(france_clean[[#This Row],[Nationality 1]],continent!A:B,2,FALSE),"") -> Africa
B70: Mathieu Lailler | C70: Goalkeeper | D70: Feb 26, 1986 | E70: 38 | F70: France | G70: France | H70: Redon | I70: 1.8 | J70: - | L70: France | P70: Bretagne | Q70: Ille-et-Vilaine | R70: =IFERROR(VLOOKUP(france_clean[[#This Row],[Nationality 1]],continent!A:B,2,FALSE),"") -> France
B71: Paul Cattier | C71: Goalkeeper | D71: May 1, 1986 | E71: 37 | F71: France | G71: France | H71: Avignon | I71: 1.87 | J71: - | L71: France | P71: Provence-Alpes-Côte d'Azur | Q71: Vaucluse | R71: =IFERROR(VLOOKUP(france_clean[[#This Row],[Nationality 1]],continent!A:B,2,FALSE),"") -> France
B72: Damien Perquis | C72: Goalkeeper | D72: Mar 8, 1986 | E72: 37 | F72: France | G72: France | H72: Saint-Brieuc | I72: 1.86 | J72: - | L72: France | P72: Bretagne | Q72: Côtes-d'Armor | R72: =IFERROR(VLOOKUP(france_clean[[#This Row],[Nationality 1]],continent!A:B,2,FALSE),"") -> France
B73: Vincent Briant | C73: Goalkeeper | D73: Sep 9, 1986 | E73: 37 | F73: France | G73: France | H73: Quimperle | I73: 1.84 | J73: - | L73: France | P73: Bretagne | Q73: Finistère | R73: =IFERROR(VLOOKUP(france_clean[[#This Row],[Nationality 1]],continent!A:B,2,FALSE),"") -> France
B74: Thibault Ferrand | C74: Goalkeeper | D74: Mar 26, 1986 | E74: 37 | F74: France | G74: France | H74: Chambray-les-Tours | I74: 1.83 | J74: - | L74: France | R74: =IFERROR(VLOOKUP(france_clean[[#This Row],[Nationality 1]],continent!A:B,2,FALSE),"") -> France
B75: Jessy Moulin | C75: Goalkeeper | D75: Jan 13, 1986 | E75: 38 | F75: France | G75: France | H75: Valence | I75: 1.84 | J75: - | L75: France | P75: Nouvelle-Aquitaine | Q75: Charente | R75: =IFERROR(VLOOKUP(france_clean[[#This Row],[Nationality 1]],continent!A:B,2,FALSE),"") -> France
B76: Geoffrey Jourdren | C76: Goalkeeper | D76: Feb 4, 1986 | E76: 38 | F76: France | G76: France | H76: Meaux | I76: 1.83 | J76: - | L76: France | P76: Île-de-France | Q76: Seine-et-Marne | R76: =IFERROR(VLOOKUP(france_clean[[#This Row],[Nationality 1]],continent!A:B,2,FALSE),"") -> France
B77: Stéphane Véron | C77: Goalkeeper | D77: Jan 31, 1986 | E77: 38 | F77: France, Argentina | G77: France | H77: Sens | I77: 1.86 | J77: - | L77: France | M77: Argentina | P77: Bourgogne-Franche-Comté | Q77: Yonne | R77: =IFERROR(VLOOKUP(france_clean[[#This Row],[Nationality 1]],continent!A:B,2,FALSE),"") -> France
A78: 56 | B78: Benoît Costil | C78: Goalkeeper | D78: Jul 3, 1987 | E78: 36 | F78: France | G78: France | H78: Caen | I78: 1.88 | J78: €800k | L78: France | P78: Normandie | Q78: Calvados | R78: =IFERROR(VLOOKUP(france_clean[[#This Row],[Nationality 1]],continent!A:B,2,FALSE),"") -> France
A79: 88 | B79: Gilles Meyer | C79: Goalkeeper | D79: Dec 9, 1987 | E79: 36 | F79: France | G79: France | H79: Strasbourg | I79: 1.8 | J79: €10k | L79: France | P79: Grand Est | Q79: Bas-Rhin | R79: =IFERROR(VLOOKUP(france_clean[[#This Row],[Nationality 1]],continent!A:B,2,FALSE),"") -> France
B80: Cédric Malavaud | C80: Goalkeeper | D80: May 18, 1987 | E80: 36 | F80: France | G80: France | H80: Gueret | I80: 1.8 | J80: - | L80: France | P80: Nouvelle-Aquitaine | Q80: Creuse | R80: =IFERROR(VLOOKUP(france_clean[[#This Row],[Nationality 1]],continent!A:B,2,FALSE),"") -> France
B81: Xavier Poinot | C81: Goalkeeper | D81: Oct 20, 1987 | E81: 36 | F81: France | G81: France | H81: Poitiers | J81: - | L81: France | P81: Nouvelle-Aquitaine | Q81: Vienne | R81: =IFERROR(VLOOKUP(france_clean[[#This Row],[Nationality 1]],continent!A:B,2,FALSE),"") -> France
B82: Jawad Khacime | C82: Goalkeeper | D82: Jul 11, 1987 | E82: 36 | F82: France, Morocco | G82: France | H82: Bourges | I82: 1.76 | J82: - | L82: France | M82: Morocco | P82: Centre-Val de Loire | Q82: Cher | R82: =IFERROR(VLOOKUP(france_clean[[#This Row],[Nationality 1]],continent!A:B,2,FALSE),"") -> France
B83: Jérémy Tomaselli | C83: Goalkeeper | D83: Jun 27, 1987 | E83: 36 | F83: Saint-Martin, France | G83: France | H83: Nice | I83: 1.75 | J83: - | L83: Saint-Martin | M83: France | P83: Provence-Alpes-Côte d'Azur | Q83: Alpes-Maritimes | R83: =IFERROR(VLOOKUP(france_clean[[#This Row],[Nationality 1]],continent!A:B,2,FALSE),"") -> North America
B84: Jean-Baptiste Habert | C84: Goalkeeper | D84: Feb 24, 1987 | E84: 37 | F84: France | G84: France | H84: Montargis | I84: 1.83 | J84: - | L84: France | P84: Centre-Val de Loire | Q84: Loiret | R84: =IFERROR(VLOOKUP(france_clean[[#This Row],[Nationality 1]],continent!A:B,2,FALSE),"") -> France
B85: Mickaël Scanella | C85: Goalkeeper | D85: Jun 10, 1987 | E85: 36 | F85: France | G85: France | H85: Echirolles | I85: 1.8 | J85: - | L85: France | P85: Auvergne-Rhône-Alpes | Q85: Isère | R85: =IFERROR(VLOOKUP(france_clean[[#This Row],[Nationality 1]],continent!A:B,2,FALSE),"") -> France
B86: Mathieu Delahaigue | C86: Goalkeeper | D86: Dec 31, 1987 | E86: 36 | F86: France | G86: France | H86: Sainte-Foy-les-Lyon | I86: 1.79 | J86: - | L86: France | R86: =IFERROR(VLOOKUP(france_clean[[#This Row],[Nationality 1]],continent!A:B,2,FALSE),"") -> France
B87: Hendrick Rivière | C87: Goalkeeper | D87: Mar 22, 1987 | E87: 36 | F87: France | G87: France | H87: Toulouse | I87: 1.84 | J87: - | L87: France | P87: Occitanie | Q87: Haute-Garonne | R87: =IFERROR(VLOOKUP(france_clean[[#This Row],[Nationality 1]],continent!A:B,2,FALSE),"") -> France
B88: Thomas Hym | C88: Goalkeeper | D88: Aug 29, 1987 | E88: 36 | F88: France | G88: France | H88: Nancy | J88: - | L88: France | P88: Grand Est | Q88: Meurthe-et-Moselle | R88: =IFERROR(VLOOKUP(france_clean[[#This Row],[Nationality 1]],continent!A:B,2,FALSE),"") -> France
B89: Anthony Cottier | C89: Goalkeeper | D89: Mar 23, 1987 | E89: 36 | F89: France | G89: France | H89: Lyon | I89: 1.83 | J89: - | L89: France | P89: Auvergne-Rhône-Alpes | Q89: Rhône | R89: =IFERROR(VLOOKUP(france_clean[[#This Row],[Nationality 1]],continent!A:B,2,FALSE),"") -> France
B90: Denis Ribeiro | C90: Goalkeeper | D90: Sep 6, 1987 | E90: 36 | F90: France | G90: France | H90: Tours | I90: 1.81 | J90: - | L90: France | P90: Centre-Val de Loire | Q90: Indre-et-Loire | R90: =IFERROR(VLOOKUP(france_clean[[#This Row],[Nationality 1]],continent!A:B,2,FALSE),"") -> France
A91: 1 | B91: Rémy Riou | C91: Goalkeeper | D91: Aug 6, 1987 | E91: 36 | F91: France | G91: France | H91: Lyon | I91: 1.91 | J91: €400k | L91: France | P91: Auvergne-Rhône-Alpes | Q91: Rhône | R91: =IFERROR(VLOOKUP(france_clean[[#This Row],[Nationality 1]],continent!A:B,2,FALSE),"") -> France
B92: Nicolas Panteghini | C92: Goalkeeper | D92: Jul 4, 1987 | E92: 36 | F92: France | G92: France | H92: Roanne | I92: 1.89 | J92: - | L92: France | P92: Auvergne-Rhône-Alpes | Q92: Loire | R92: =IFERROR(VLOOKUP(france_clean[[#This Row],[Nationality 1]],continent!A:B,2,FALSE),"") -> France
B93: Jérémy Lemaître | C93: Goalkeeper | D93: Nov 30, 1987 | E93: 36 | F93: France | G93: France | H93: Nantes | J93: - | L93: France | P93: Pays de la Loire | Q93: Loire-Atlantique | R93: =IFERROR(VLOOKUP(france_clean[[#This Row],[Nationality 1]],continent!A:B,2,FALSE),"") -> France
B94: Romain Samson | C94: Goalkeeper | D94: Aug 19, 1987 | E94: 36 | F94: France | G94: France | H94: Evreux | I94: 1.78 | J94: - | L94: France | P94: Normandie | Q94: Eure | R94: =IFERROR(VLOOKUP(france_clean[[#This Row],[Nationality 1]],continent!A:B,2,FALSE),"") -> France
B95: Jonathan Le Roux | C95: Goalkeeper | D95: Jan 24, 1987 | E95: 37 | F95: France | G95: France | H95: Vannes | I95: 1.82 | J95: - | L95: France | P95: Bretagne | Q95: Morbihan | R95: =IFERROR(VLOOKUP(france_clean[[#This Row],[Nationality 1]],continent!A:B,2,FALSE),"") -> France
B96: Bertrand Venail | C96: Goalkeeper | D96: Mar 4, 1987 | E96: 36 | F96: France | G96: France | H96: Paris | I96: 1.88 | J96: - | L96: France | P96: Île-de-France | Q96: Paris | R96: =IFERROR(VLOOKUP(france_clean[[#This Row],[Nationality 1]],continent!A:B,2,FALSE),"") -> France
B97: Dimitri Baluteau | C97: Goalkeeper | D97: May 28, 1987 | E97: 36 | F97: France | G97: France | H97: Thouars | I97: 1.76 | J97: - | L97: France | P97: Nouvelle-Aquitaine | Q97: Deux-Sèvres | R97: =IFERROR(VLOOKUP(france_clean[[#This Row],[Nationality 1]],continent!A:B,2,FALSE),"") -> France
B98: Pascal Elissalde | C98: Goalkeeper | D98: Jan 14, 1987 | E98: 37 | F98: France | G98: France | H98: Saint-Jean-de-Luz | I98: 1.81 | J98: - | L98: France | P98: Nouvelle-Aquitaine | Q98: Pyrénées-Atlantiques | R98: =IFERROR(VLOOKUP(france_clean[[#This Row],[Nationality 1]],continent!A:B,2,FALSE),"") -> France
B99: Jean-Marc Le Rouzic | C99: Goalkeeper | D99: May 14, 1987 | E99: 36 | F99: France | G99: France | H99: Auray | I99: 1.82 | J99: - | L99: France | P99: Bretagne | Q99: Morbihan | R99: =IFERROR(VLOOKUP(france_clean[[#This Row],[Nationality 1]],continent!A:B,2,FALSE),"") -> France
B100: Arnaud Gibert | C100: Goalkeeper | D100: Aug 16, 1987 | E100: 36 | F100: France | G100: France | H100: Argentan | I100: 1.93 | J100: - | L100: France | P100: Normandie | Q100: Orne | R100: =IFERROR(VLOOKUP(france_clean[[#This Row],[Nationality 1]],continent!A:B,2,FALSE),"") -> France
...

Sheet continent
A1: country | B1: continent
A2: Afghanistan | B2: Asia
A3: Albania | B3: Europe
A4: Algeria | B4: Africa
A5: American Samoa | B5: Oceania
A6: Andorra | B6: Europe
A7: Angola | B7: Africa
A8: Anguilla | B8: North America
A9: Antigua and Barbuda | B9: North America
A10: Argentina | B10: South America
A11: Armenia | B11: Asia
A12: Aruba | B12: North America
... A241: Wales | B241: Europe
A242: Macau
A243: The Gambia | B243: Africa
A244: Neukaledonien | B244: Oceania
A245: Réunion | B245: Africa

Sheet France_regions_departments
A1: name | B1: Région | C1: Département
A2: L'Abergement-Clemenciat | B2: Auvergne-Rhône-Alpes | C2: Ain
A3: L'Abergement-de-Varey | B3: Auvergne-Rhône-Alpes | C3: Ain
A4: Amberieu-en-Bugey | B4: Auvergne-Rhône-Alpes | C4: Ain
A5: Amberieux-en-Dombes | B5: Auvergne-Rhône-Alpes | C5: Ain
A6: Ambleon | B6: Auvergne-Rhône-Alpes | C6: Ain
A7: Ambronay | B7: Auvergne-Rhône-Alpes | C7: Ain
A8: Ambutrix | B8: Auvergne-Rhône-Alpes | C8: Ain
A9: Andert-et-Condon | B9: Auvergne-Rhône-Alpes | C9: Ain
A10: Anglefort | B10: Auvergne-Rhône-Alpes | C10: Ain
A11: Apremont | B11: Auvergne-Rhône-Alpes | C11: Ain
A12: Aranc | B12: Auvergne-Rhône-Alpes | C12: Ain
... A15: Arboys en Bugey | B15: Auvergne-Rhône-Alpes | C15: Ain
A16: Arbignieu
A17: Arbigny | B17: Auvergne-Rhône-Alpes | C17: Ain
A18: Argis | B18: Auvergne-Rhône-Alpes | C18: Ain
A19: Armix | B19: Auvergne-Rhône-Alpes | C19: Ain
A20: Ars-sur-Formans | B20: Auvergne-Rhône-Alpes | C20: Ain
A21: Artemare | B21: Auvergne-Rhône-Alpes | C21: Ain
A22: Asnières-sur-Saône | B22: Auvergne-Rhône-Alpes | C22: Ain
A23: Attignat | B23: Auvergne-Rhône-Alpes | C23: Ain
A24: Bâge-Dommartin | B24: Auvergne-Rhône-Alpes | C24: Ain
A25: Bâge-la-Ville
A26: Bâge-le-Châtel | B26: Auvergne-Rhône-Alpes | C26: Ain
A27: Balan | B27: Auvergne-Rhône-Alpes | C27: Ain
A28: Baneins | B28: Auvergne-Rhône-Alpes | C28: Ain
A29: Beaupont | B29: Auvergne-Rhône-Alpes | C29: Ain
A30: Beauregard | B30: Auvergne-Rhône-Alpes | C30: Ain
A31: Bellignat | B31: Auvergne-Rhône-Alpes | C31: Ain
A32: Beligneux | B32: Auvergne-Rhône-Alpes | C32: Ain
A33: Valserhône | B33: Auvergne-Rhône-Alpes | C33: Ain
A34: Bellegarde-sur-Valserine
A35: Belley | B35: Auvergne-Rhône-Alpes | C35: Ain
A36: Belleydoux | B36: Auvergne-Rhône-Alpes | C36: Ain
A37: Valromey-sur-Seran | B37: Auvergne-Rhône-Alpes | C37: Ain
A38: Belmont-Luthezieu
A39: Benonces | B39: Auvergne-Rhône-Alpes | C39: Ain
A40: Beny | B40: Auvergne-Rhône-Alpes | C40: Ain
A41: Beon
A42: Bereziat | B42: Auvergne-Rhône-Alpes | C42: Ain
A43: Bettant | B43: Auvergne-Rhône-Alpes | C43: Ain
A44: Bey | B44: Auvergne-Rhône-Alpes | C44: Ain
A45: Beynost | B45: Auvergne-Rhône-Alpes | C45: Ain
A46: Billiat | B46: Auvergne-Rhône-Alpes | C46: Ain
A47: Birieux | B47: Auvergne-Rhône-Alpes | C47: Ain
A48: Biziat | B48: Auvergne-Rhône-Alpes | C48: Ain
A49: Blyes | B49: Auvergne-Rhône-Alpes | C49: Ain
A50: La Boisse | B50: Auvergne-Rhône-Alpes | C50: Ain
A51: Boissey | B51: Auvergne-Rhône-Alpes | C51: Ain
A52: Bolozon | B52: Auvergne-Rhône-Alpes | C52: Ain
A53: Bouligneux | B53: Auvergne-Rhône-Alpes | C53: Ain
... A58: Bregnier-Cordon | B58: Auvergne-Rhône-Alpes | C58: Ain
A59: Brenaz
A60: Brenod | B60: Auvergne-Rhône-Alpes | C60: Ain
A61: Brens | B61: Auvergne-Rhône-Alpes | C61: Ain
A62: Bressolles | B62: Auvergne-Rhône-Alpes | C62: Ain
A63: Brion | B63: Auvergne-Rhône-Alpes | C63: Ain
A64: Briord | B64: Auvergne-Rhône-Alpes | C64: Ain
A65: Buellas | B65: Auvergne-Rhône-Alpes | C65: Ain
A66: La Burbanche | B66: Auvergne-Rhône-Alpes | C66: Ain
A67: Ceignes | B67: Auvergne-Rhône-Alpes | C67: Ain
A68: Cerdon | B68: Auvergne-Rhône-Alpes | C68: Ain
A69: Certines | B69: Auvergne-Rhône-Alpes | C69: Ain
A70: Cessy | B70: Auvergne-Rhône-Alpes | C70: Ain
A71: Ceyzeriat | B71: Auvergne-Rhône-Alpes | C71: Ain
... A79: Champdor-Corcelles | B79: Auvergne-Rhône-Alpes | C79: Ain
A80: Champdor
A81: Champfromier | B81: Auvergne-Rhône-Alpes | C81: Ain
A82: Chanay | B82: Auvergne-Rhône-Alpes | C82: Ain
A83: Chaneins | B83: Auvergne-Rhône-Alpes | C83: Ain
A84: Chanoz-Châtenay | B84: Auvergne-Rhône-Alpes | C84: Ain
A85: La Chapelle-du-Châtelard | B85: Auvergne-Rhône-Alpes | C85: Ain
A86: Charix | B86: Auvergne-Rhône-Alpes | C86: Ain
A87: Charnoz-sur-Ain | B87: Auvergne-Rhône-Alpes | C87: Ain
A88: Château-Gaillard | B88: Auvergne-Rhône-Alpes | C88: Ain
A89: Châtenay | B89: Auvergne-Rhône-Alpes | C89: Ain
A90: Châtillon-en-Michaille
A91: Châtillon-la-Palud | B91: Auvergne-Rhône-Alpes | C91: Ain
A92: Châtillon-sur-Chalaronne | B92: Auvergne-Rhône-Alpes | C92: Ain
A93: Chavannes-sur-Reyssouze | B93: Auvergne-Rhône-Alpes | C93: Ain
A94: Nivigne et Suran | B94: Auvergne-Rhône-Alpes | C94: Ain
A95: Chaveyriat | B95: Auvergne-Rhône-Alpes | C95: Ain
A96: Chavornay
A97: Chazey-Bons | B97: Auvergne-Rhône-Alpes | C97: Ain
A98: Chazey-sur-Ain | B98: Auvergne-Rhône-Alpes | C98: Ain
A99: Cheignieu-la-Balme | B99: Auvergne-Rhône-Alpes | C99: Ain
A100: Chevillard | B100: Auvergne-Rhône-Alpes | C100: Ain
A101: Chevroux | B101: Auvergne-Rhône-Alpes | C101: Ain
A102: Chevry | B102: Auvergne-Rhône-Alpes | C102: Ain
A103: Chezery-Forens | B103: Auvergne-Rhône-Alpes | C103: Ain
A104: Civrieux | B104: Auvergne-Rhône-Alpes | C104: Ain
A105: Cize | B105: Auvergne-Rhône-Alpes | C105: Ain
A106: Cleyzieu | B106: Auvergne-Rhône-Alpes | C106: Ain
A107: Coligny | B107: Auvergne-Rhône-Alpes | C107: Ain
A108: Collonges | B108: Auvergne-Rhône-Alpes | C108: Ain
... A117: Corbonod | B117: Auvergne-Rhône-Alpes | C117: Ain
A118: Corcelles
A119: Cordieux
A120: Corlier | B120: Auvergne-Rhône-Alpes | C120: Ain
A121: Cormaranche-en-Bugey
...

Sheet TCD
A1: Region | B1: Île-de-France
A2: Nationality 1 | B2: (Tous)
A3: Nationality 2 | B3: (Tous)
A5: Étiquettes de lignes | B5: Nombre de Name
A6: France | B6: 1570 | E6: 1570 | F6: =E6/GETPIVOTDATA("Name",$A$5) -> 0.73605251 | I6: 6647 | J6: =I6/GETPIVOTDATA("Name",$A$5) -> 3.1162682
A7: Africa | B7: 377 | E7: 356 | F7: =E7/GETPIVOTDATA("Name",$A$5) -> 0.16690108 | I7: 1113 | J7: =I7/GETPIVOTDATA("Name",$A$5) -> 0.52180028
A8: North America | B8: 91 | E8: 91 | F8: =E8/GETPIVOTDATA("Name",$A$5) -> 0.042662916 | I8: 218 | J8: =I8/GETPIVOTDATA("Name",$A$5) -> 0.10220347
A9: Europe | B9: 58 | E9: 57 | F9: =E9/GETPIVOTDATA("Name",$A$5) -> 0.026722925 | I9: 145 | J9: =I9/GETPIVOTDATA("Name",$A$5) -> 0.067979372
A10: Asia | B10: 25 | E10: 14 | F10: =E10/GETPIVOTDATA("Name",$A$5) -> 0.0065635256 | I10: 144 | J10: =I10/GETPIVOTDATA("Name",$A$5) -> 0.067510549
A11: South America | B11: 10 | E11: 10 | F11: =E11/GETPIVOTDATA("Name",$A$5) -> 0.0046882325 | I11: 18 | J11: =I11/GETPIVOTDATA("Name",$A$5) -> 0.0084388186
A12: Oceania | B12: 2 | E12: 2 | F12: =E12/GETPIVOTDATA("Name",$A$5) -> 0.00093764651 | I12: 6 | J12: =I12/GETPIVOTDATA("Name",$A$5) -> 0.0028129395
A13: Total général | B13: 2133
